basek2/__init__.py
basek2/player.py
basek2/team.py
basetest1-0.0.0.2.dist-info/METADATA
basetest1-0.0.0.2.dist-info/WHEEL
basetest1-0.0.0.2.dist-info/top_level.txt
basetest1-0.0.0.2.dist-info/RECORD
